Metadata-Version: 2.1
Name: foxrandompy
Version: 2022.0.3
Summary: Данная библиотека предназначена для рандома, вся информация в документации!
Author: Ginji
Author-email: bfire1999@gmail.com
License: Apache License, Version 2.0, see LICENSE file
Platform: UNKNOWN
